qualibrate_config/__init__.py
qualibrate_config/__main__.py
qualibrate_config/cli/__init__.py
qualibrate_config/cli/config.py
qualibrate_config/cli/deprecated/__init__.py
qualibrate_config/cli/deprecated/deprecated_option.py
qualibrate_config/cli/deprecated/deprecated_options_command.py
qualibrate_config/cli/migrate.py
qualibrate_config/cli/migrations/__init__.py
qualibrate_config/cli/migrations/base.py
qualibrate_config/cli/project/__init__.py
qualibrate_config/cli/project/commands/__init__.py
qualibrate_config/cli/project/commands/create.py
qualibrate_config/cli/project/commands/current.py
qualibrate_config/cli/project/commands/delete.py
qualibrate_config/cli/project/commands/list.py
qualibrate_config/cli/project/commands/switch.py
qualibrate_config/cli/project/group.py
qualibrate_config/cli/utils/__init__.py
qualibrate_config/cli/utils/content.py
qualibrate_config/cli/utils/from_sources.py
qualibrate_config/cli/utils/migration_utils.py
qualibrate_config/cli/vars.py
qualibrate_config/core/__init__.py
qualibrate_config/core/approve.py
qualibrate_config/core/content.py
qualibrate_config/core/defaults.py
qualibrate_config/core/from_sources.py
qualibrate_config/core/migration/__init__.py
qualibrate_config/core/migration/migrate.py
qualibrate_config/core/migration/migrations/__init__.py
qualibrate_config/core/migration/migrations/base.py
qualibrate_config/core/migration/migrations/v1_v2.py
qualibrate_config/core/migration/migrations/v2_v3.py
qualibrate_config/core/migration/migrations/v3_v4.py
qualibrate_config/core/migration/migrations/v4_v5.py
qualibrate_config/core/migration/utils.py
qualibrate_config/core/project/__init__.py
qualibrate_config/core/project/active.py
qualibrate_config/core/project/common.py
qualibrate_config/core/project/create.py
qualibrate_config/core/project/delete.py
qualibrate_config/core/project/model.py
qualibrate_config/core/project/p_list.py
qualibrate_config/core/project/path.py
qualibrate_config/core/project/switch.py
qualibrate_config-0.1.8.dist-info/METADATA
qualibrate_config-0.1.8.dist-info/WHEEL
qualibrate_config-0.1.8.dist-info/entry_points.txt
qualibrate_config-0.1.8.dist-info/licenses/LICENSE
qualibrate_config-0.1.8.dist-info/RECORD
